{
    "sheet_name": "PremiseAreaHistory",
    "enabled": true,
    "mandatory_fields":["AreaId", "Measure"] ,
    "mappings": {
        "AreaId": {
            "external_column": "",
            "regex": "",
            "description": "",
            "default": ""
        },
        "Details": {
            "external_column": "",
            "regex": "",
            "description": "",
            "default": ""
        },
        "StartDate": {
            "external_column": "",
            "regex": "",
            "description": "",
            "default": ""
        },
        "EndDate": {
            "external_column": "",
            "regex": "",
            "description": "",
            "default": ""
        },
        "Floor": {
            "external_column": "",
            "regex": "",
            "description": "",
            "default": ""
        },
        "Measure": {
            "external_column": "",
            "regex": "",
            "description": "",
            "default": ""
        },
        "Suite": {
            "external_column": "",
            "regex": "",
            "description": "",
            "default": ""
        }
    }
}
