{
    "sheet_name": "LocationToPartnerContact",
    "enabled": true,
    "mandatory_fields": [],
    "mappings": {
        "LocationToPartnerId": {
            "external_column": "",
            "regex": "",
            "description": "",
            "default": ""
        },
        "ContactId": {
            "external_column": "",
            "regex": "",
            "description": "",
            "default": ""
        },
        "Address": {
            "external_column": "",
            "regex": "",
            "description": "",
            "default": ""
        },
        "Description": {
            "external_column": "",
            "regex": "",
            "description": "",
            "default": ""
        },
        "Email": {
            "external_column": "",
            "regex": "",
            "description": "",
            "default": ""
        },
        "Name": {
            "external_column": "",
            "regex": "",
            "description": "",
            "default": ""
        },
        "Phone": {
            "external_column": "",
            "regex": "",
            "description": "",
            "default": ""
        },
        "Position": {
            "external_column": "",
            "regex": "",
            "description": "",
            "default": ""
        },
        "Fax": {
            "external_column": "",
            "regex": "",
            "description": "",
            "default": ""
        },
        "ContactTypes": {
            "external_column": "",
            "regex": "",
            "description": "",
            "default": ""
        }
    }
}